symmetria_core-0.4.3.dist-info/METADATA
symmetria_core-0.4.3.dist-info/WHEEL
symmetria_core/__init__.py
symmetria_core/_symmetria_core.cpython-313t-arm-linux-gnueabihf.so
symmetria_core/_symmetria_core.pyi
symmetria_core/cycle.pyi
symmetria_core/permutation.pyi
symmetria_core/py.tiped
symmetria_core/table.pyi
symmetria_core/validators.pyi
symmetria_core-0.4.3.dist-info/RECORD
