Metadata-Version: 2.4
Name: symmetria_core
Version: 0.4.3
Classifier: Programming Language :: Rust
Classifier: Programming Language :: Python :: Implementation :: CPython
Classifier: Programming Language :: Python :: Implementation :: PyPy
Requires-Dist: maturin>=1.9.4
Requires-Python: >=3.9
